<?xml version="1.0"?>
<BinaryTree boostWeight="1.0000000000000000e+00" itree="232" type="DecisionTree">
      <Node Cut="-6.6000000000000000e+01" IVar="2" NCoef="0" cType="1" depth="0" nType="0" pos="s" purity="0.0000000000000000e+00" res="0.0000000000000000e+00" rms="0.0000000000000000e+00">
        <Node Cut="-6.7000000000000000e+01" IVar="2" NCoef="0" cType="1" depth="1" nType="0" pos="l" purity="0.0000000000000000e+00" res="0.0000000000000000e+00" rms="0.0000000000000000e+00">
          <Node Cut="1.9100000000000000e+02" IVar="3" NCoef="0" cType="1" depth="2" nType="0" pos="l" purity="0.0000000000000000e+00" res="8.2068234682083130e-01" rms="-nan">
            <Node Cut="1.7400000000000000e+02" IVar="3" NCoef="0" cType="1" depth="3" nType="0" pos="l" purity="0.0000000000000000e+00" res="-4.4297236949205399e-02" rms="-nan">
              <Node Cut="8.0000000000000000e+00" IVar="0" NCoef="0" cType="1" depth="4" nType="0" pos="l" purity="0.0000000000000000e+00" res="5.0551532767713070e-03" rms="3.6582708358764648e-01">
                <Node Cut="0.0000000000000000e+00" IVar="-1" NCoef="0" cType="1" depth="5" nType="-99" pos="l" purity="0.0000000000000000e+00" res="1.1436725966632366e-02" rms="5.6201583147048950e-01" />
                <Node Cut="0.0000000000000000e+00" IVar="-1" NCoef="0" cType="1" depth="5" nType="-99" pos="r" purity="0.0000000000000000e+00" res="2.8256172663532197e-04" rms="3.6037206649780273e-01" />
              </Node>
              <Node Cut="-1.4300000000000000e+02" IVar="2" NCoef="0" cType="1" depth="4" nType="0" pos="r" purity="0.0000000000000000e+00" res="0.0000000000000000e+00" rms="0.0000000000000000e+00">
                <Node Cut="0.0000000000000000e+00" IVar="-1" NCoef="0" cType="1" depth="5" nType="-99" pos="l" purity="0.0000000000000000e+00" res="2.0765897352248430e-03" rms="3.3854809403419495e-01" />
                <Node Cut="0.0000000000000000e+00" IVar="-1" NCoef="0" cType="1" depth="5" nType="-99" pos="r" purity="0.0000000000000000e+00" res="1.0620171204209328e-02" rms="3.4408038854598999e-01" />
              </Node>
            </Node>
            <Node Cut="0.0000000000000000e+00" IVar="7" NCoef="0" cType="1" depth="3" nType="0" pos="r" purity="0.0000000000000000e+00" res="-1.7099226824939251e-03" rms="8.8441878557205200e-02">
              <Node Cut="-1.0000000000000000e+00" IVar="8" NCoef="0" cType="1" depth="4" nType="0" pos="l" purity="0.0000000000000000e+00" res="-1.9712294451892376e-03" rms="9.6954420208930969e-02">
                <Node Cut="0.0000000000000000e+00" IVar="-1" NCoef="0" cType="1" depth="5" nType="-99" pos="l" purity="0.0000000000000000e+00" res="8.8803493417799473e-04" rms="1.4789226651191711e-01" />
                <Node Cut="0.0000000000000000e+00" IVar="-1" NCoef="0" cType="1" depth="5" nType="-99" pos="r" purity="0.0000000000000000e+00" res="-1.7380368662998080e-03" rms="1.5912857651710510e-01" />
              </Node>
              <Node Cut="2.4400000000000000e+02" IVar="4" NCoef="0" cType="1" depth="4" nType="0" pos="r" purity="0.0000000000000000e+00" res="3.5020440816879272e-02" rms="1.8714970350265503e-01">
                <Node Cut="0.0000000000000000e+00" IVar="-1" NCoef="0" cType="1" depth="5" nType="-99" pos="l" purity="0.0000000000000000e+00" res="-9.2542264610528946e-03" rms="4.6518400311470032e-01" />
                <Node Cut="0.0000000000000000e+00" IVar="-1" NCoef="0" cType="1" depth="5" nType="-99" pos="r" purity="0.0000000000000000e+00" res="2.6691988110542297e-01" rms="0.0000000000000000e+00" />
              </Node>
            </Node>
          </Node>
          <Node Cut="2.4000000000000000e+01" IVar="0" NCoef="0" cType="1" depth="2" nType="0" pos="r" purity="0.0000000000000000e+00" res="1.5879073739051819e-01" rms="6.3106781244277954e-01">
            <Node Cut="1.0000000000000000e+00" IVar="7" NCoef="0" cType="1" depth="3" nType="0" pos="l" purity="0.0000000000000000e+00" res="4.3991219997406006e-01" rms="7.1934074163436890e-01">
              <Node Cut="0.0000000000000000e+00" IVar="7" NCoef="0" cType="1" depth="4" nType="0" pos="l" purity="0.0000000000000000e+00" res="2.2495675086975098e-01" rms="4.9386191368103027e-01">
                <Node Cut="0.0000000000000000e+00" IVar="-1" NCoef="0" cType="1" depth="5" nType="-99" pos="l" purity="0.0000000000000000e+00" res="4.0856423974037170e-01" rms="0.0000000000000000e+00" />
                <Node Cut="0.0000000000000000e+00" IVar="-1" NCoef="0" cType="1" depth="5" nType="-99" pos="r" purity="0.0000000000000000e+00" res="8.8878743350505829e-02" rms="7.3817157745361328e-01" />
              </Node>
              <Node Cut="1.0000000000000000e+00" IVar="6" NCoef="0" cType="1" depth="4" nType="0" pos="r" purity="0.0000000000000000e+00" res="1.2872835397720337e+00" rms="1.8448811769485474e+00">
                <Node Cut="0.0000000000000000e+00" IVar="-1" NCoef="0" cType="1" depth="5" nType="-99" pos="l" purity="0.0000000000000000e+00" res="2.4215330183506012e-01" rms="0.0000000000000000e+00" />
                <Node Cut="0.0000000000000000e+00" IVar="-1" NCoef="0" cType="1" depth="5" nType="-99" pos="r" purity="0.0000000000000000e+00" res="3.9312905073165894e-01" rms="0.0000000000000000e+00" />
              </Node>
            </Node>
            <Node Cut="1.0000000000000000e+00" IVar="6" NCoef="0" cType="1" depth="3" nType="0" pos="r" purity="0.0000000000000000e+00" res="-8.9599164202809334e-03" rms="6.9913327693939209e-02">
              <Node Cut="1.0000000000000000e+00" IVar="7" NCoef="0" cType="1" depth="4" nType="0" pos="l" purity="0.0000000000000000e+00" res="-1.1577472090721130e-02" rms="3.0589450150728226e-02">
                <Node Cut="0.0000000000000000e+00" IVar="-1" NCoef="0" cType="1" depth="5" nType="-99" pos="l" purity="0.0000000000000000e+00" res="-2.2425875067710876e-03" rms="2.8473743796348572e-01" />
                <Node Cut="0.0000000000000000e+00" IVar="-1" NCoef="0" cType="1" depth="5" nType="-99" pos="r" purity="0.0000000000000000e+00" res="-5.2094452083110809e-02" rms="2.8024658560752869e-01" />
              </Node>
              <Node Cut="3.8000000000000000e+01" IVar="3" NCoef="0" cType="1" depth="4" nType="0" pos="r" purity="0.0000000000000000e+00" res="1.4653961174190044e-02" rms="-nan">
                <Node Cut="0.0000000000000000e+00" IVar="-1" NCoef="0" cType="1" depth="5" nType="-99" pos="l" purity="0.0000000000000000e+00" res="1.7007845640182495e-01" rms="1.2082536518573761e-01" />
                <Node Cut="0.0000000000000000e+00" IVar="-1" NCoef="0" cType="1" depth="5" nType="-99" pos="r" purity="0.0000000000000000e+00" res="2.0186734199523926e-01" rms="0.0000000000000000e+00" />
              </Node>
            </Node>
          </Node>
        </Node>
        <Node Cut="-5.6000000000000000e+01" IVar="4" NCoef="0" cType="1" depth="1" nType="0" pos="r" purity="0.0000000000000000e+00" res="0.0000000000000000e+00" rms="0.0000000000000000e+00">
          <Node Cut="5.5000000000000000e+01" IVar="0" NCoef="0" cType="1" depth="2" nType="0" pos="l" purity="0.0000000000000000e+00" res="-2.1393901109695435e-01" rms="5.9565365314483643e-01">
            <Node Cut="1.0000000000000000e+00" IVar="8" NCoef="0" cType="1" depth="3" nType="0" pos="l" purity="0.0000000000000000e+00" res="-2.0749530196189880e-01" rms="3.7327900528907776e-01">
              <Node Cut="1.0000000000000000e+00" IVar="7" NCoef="0" cType="1" depth="4" nType="0" pos="l" purity="0.0000000000000000e+00" res="-2.2843533754348755e-01" rms="2.8253594040870667e-01">
                <Node Cut="0.0000000000000000e+00" IVar="-1" NCoef="0" cType="1" depth="5" nType="-99" pos="l" purity="0.0000000000000000e+00" res="-4.9641262739896774e-02" rms="4.7384274005889893e-01" />
                <Node Cut="0.0000000000000000e+00" IVar="-1" NCoef="0" cType="1" depth="5" nType="-99" pos="r" purity="0.0000000000000000e+00" res="3.9924930781126022e-02" rms="1.4739772081375122e+00" />
              </Node>
              <Node Cut="1.2000000000000000e+01" IVar="0" NCoef="0" cType="1" depth="4" nType="0" pos="r" purity="0.0000000000000000e+00" res="2.4388077259063721e+00" rms="4.6488016843795776e-01">
                <Node Cut="0.0000000000000000e+00" IVar="-1" NCoef="0" cType="1" depth="5" nType="-99" pos="l" purity="0.0000000000000000e+00" res="2.7893224358558655e-01" rms="0.0000000000000000e+00" />
                <Node Cut="0.0000000000000000e+00" IVar="-1" NCoef="0" cType="1" depth="5" nType="-99" pos="r" purity="0.0000000000000000e+00" res="1.8222469091415405e-01" rms="0.0000000000000000e+00" />
              </Node>
            </Node>
            <Node Cut="-5.9000000000000000e+01" IVar="4" NCoef="0" cType="1" depth="3" nType="0" pos="r" purity="0.0000000000000000e+00" res="1.0324463248252869e-01" rms="1.1041603237390518e-01">
              <Node Cut="6.8000000000000000e+01" IVar="0" NCoef="0" cType="1" depth="4" nType="0" pos="l" purity="0.0000000000000000e+00" res="1.8363317847251892e-01" rms="7.6439902186393738e-02">
                <Node Cut="0.0000000000000000e+00" IVar="-1" NCoef="0" cType="1" depth="5" nType="-99" pos="l" purity="0.0000000000000000e+00" res="2.6381039991974831e-02" rms="0.0000000000000000e+00" />
                <Node Cut="0.0000000000000000e+00" IVar="-1" NCoef="0" cType="1" depth="5" nType="-99" pos="r" purity="0.0000000000000000e+00" res="1.1075639165937901e-02" rms="0.0000000000000000e+00" />
              </Node>
              <Node Cut="6.7000000000000000e+01" IVar="0" NCoef="0" cType="1" depth="4" nType="0" pos="r" purity="0.0000000000000000e+00" res="-3.0333958566188812e-02" rms="4.3726172298192978e-02">
                <Node Cut="0.0000000000000000e+00" IVar="-1" NCoef="0" cType="1" depth="5" nType="-99" pos="l" purity="0.0000000000000000e+00" res="-8.0806639743968844e-04" rms="0.0000000000000000e+00" />
                <Node Cut="0.0000000000000000e+00" IVar="-1" NCoef="0" cType="1" depth="5" nType="-99" pos="r" purity="0.0000000000000000e+00" res="-1.1625283397734165e-02" rms="0.0000000000000000e+00" />
              </Node>
            </Node>
          </Node>
          <Node Cut="-6.5000000000000000e+01" IVar="2" NCoef="0" cType="1" depth="2" nType="0" pos="r" purity="0.0000000000000000e+00" res="0.0000000000000000e+00" rms="0.0000000000000000e+00">
            <Node Cut="4.4000000000000000e+01" IVar="3" NCoef="0" cType="1" depth="3" nType="0" pos="l" purity="0.0000000000000000e+00" res="0.0000000000000000e+00" rms="0.0000000000000000e+00">
              <Node Cut="2.5000000000000000e+01" IVar="3" NCoef="0" cType="1" depth="4" nType="0" pos="l" purity="0.0000000000000000e+00" res="-8.6355102062225342e-01" rms="6.3557982444763184e-01">
                <Node Cut="0.0000000000000000e+00" IVar="-1" NCoef="0" cType="1" depth="5" nType="-99" pos="l" purity="0.0000000000000000e+00" res="1.1736283451318741e-01" rms="4.8422199487686157e-01" />
                <Node Cut="0.0000000000000000e+00" IVar="-1" NCoef="0" cType="1" depth="5" nType="-99" pos="r" purity="0.0000000000000000e+00" res="-1.0980363190174103e-01" rms="1.7440341413021088e-01" />
              </Node>
              <Node Cut="6.0000000000000000e+01" IVar="3" NCoef="0" cType="1" depth="4" nType="0" pos="r" purity="0.0000000000000000e+00" res="0.0000000000000000e+00" rms="0.0000000000000000e+00">
                <Node Cut="0.0000000000000000e+00" IVar="-1" NCoef="0" cType="1" depth="5" nType="-99" pos="l" purity="0.0000000000000000e+00" res="1.6304060816764832e-01" rms="1.2952212095260620e+00" />
                <Node Cut="0.0000000000000000e+00" IVar="-1" NCoef="0" cType="1" depth="5" nType="-99" pos="r" purity="0.0000000000000000e+00" res="-5.7390872389078140e-03" rms="3.0330240726470947e-01" />
              </Node>
            </Node>
            <Node Cut="-3.0000000000000000e+00" IVar="8" NCoef="0" cType="1" depth="3" nType="0" pos="r" purity="0.0000000000000000e+00" res="-6.5207708394154906e-04" rms="3.1493014097213745e-01">
              <Node Cut="3.1000000000000000e+01" IVar="4" NCoef="0" cType="1" depth="4" nType="0" pos="l" purity="0.0000000000000000e+00" res="9.9572217464447021e-01" rms="-nan">
                <Node Cut="0.0000000000000000e+00" IVar="-1" NCoef="0" cType="1" depth="5" nType="-99" pos="l" purity="0.0000000000000000e+00" res="-4.3307654559612274e-03" rms="2.5829061865806580e-01" />
                <Node Cut="0.0000000000000000e+00" IVar="-1" NCoef="0" cType="1" depth="5" nType="-99" pos="r" purity="0.0000000000000000e+00" res="-4.4302087189862505e-05" rms="1.8955267965793610e-01" />
              </Node>
              <Node Cut="-4.8000000000000000e+01" IVar="4" NCoef="0" cType="1" depth="4" nType="0" pos="r" purity="0.0000000000000000e+00" res="9.9966412782669067e-01" rms="-nan">
                <Node Cut="0.0000000000000000e+00" IVar="-1" NCoef="0" cType="1" depth="5" nType="-99" pos="l" purity="0.0000000000000000e+00" res="1.8135203048586845e-02" rms="8.1358683109283447e-01" />
                <Node Cut="0.0000000000000000e+00" IVar="-1" NCoef="0" cType="1" depth="5" nType="-99" pos="r" purity="0.0000000000000000e+00" res="3.2696119887987152e-05" rms="4.1065996885299683e-01" />
              </Node>
            </Node>
          </Node>
        </Node>
      </Node>
    </BinaryTree>
    