<?xml version="1.0"?>
<BinaryTree boostWeight="1.0000000000000000e+00" itree="366" type="DecisionTree">
      <Node Cut="7.0000000000000000e+00" IVar="7" NCoef="0" cType="1" depth="0" nType="0" pos="s" purity="0.0000000000000000e+00" res="-6.8679066316690296e-05" rms="3.7695822119712830e-01">
        <Node Cut="4.0000000000000000e+00" IVar="0" NCoef="0" cType="1" depth="1" nType="0" pos="l" purity="0.0000000000000000e+00" res="-6.5148284193128347e-05" rms="3.8803434371948242e-01">
          <Node Cut="4.0000000000000000e+00" IVar="2" NCoef="0" cType="1" depth="2" nType="0" pos="l" purity="0.0000000000000000e+00" res="0.0000000000000000e+00" rms="0.0000000000000000e+00">
            <Node Cut="3.0000000000000000e+00" IVar="2" NCoef="0" cType="1" depth="3" nType="0" pos="l" purity="0.0000000000000000e+00" res="0.0000000000000000e+00" rms="0.0000000000000000e+00">
              <Node Cut="0.0000000000000000e+00" IVar="6" NCoef="0" cType="1" depth="4" nType="0" pos="l" purity="0.0000000000000000e+00" res="0.0000000000000000e+00" rms="0.0000000000000000e+00">
                <Node Cut="0.0000000000000000e+00" IVar="-1" NCoef="0" cType="1" depth="5" nType="-99" pos="l" purity="0.0000000000000000e+00" res="6.6570416092872620e-03" rms="7.6016223430633545e-01" />
                <Node Cut="0.0000000000000000e+00" IVar="-1" NCoef="0" cType="1" depth="5" nType="-99" pos="r" purity="0.0000000000000000e+00" res="-3.4759403206408024e-03" rms="1.1954584121704102e+00" />
              </Node>
              <Node Cut="3.0000000000000000e+00" IVar="7" NCoef="0" cType="1" depth="4" nType="0" pos="r" purity="0.0000000000000000e+00" res="1.0953623056411743e+00" rms="-nan">
                <Node Cut="0.0000000000000000e+00" IVar="-1" NCoef="0" cType="1" depth="5" nType="-99" pos="l" purity="0.0000000000000000e+00" res="-8.0528476973995566e-04" rms="2.8538545966148376e-01" />
                <Node Cut="0.0000000000000000e+00" IVar="-1" NCoef="0" cType="1" depth="5" nType="-99" pos="r" purity="0.0000000000000000e+00" res="1.8352083861827850e-02" rms="1.4951465129852295e+00" />
              </Node>
            </Node>
            <Node Cut="7.0000000000000000e+00" IVar="2" NCoef="0" cType="1" depth="3" nType="0" pos="r" purity="0.0000000000000000e+00" res="0.0000000000000000e+00" rms="0.0000000000000000e+00">
              <Node Cut="1.0000000000000000e+00" IVar="6" NCoef="0" cType="1" depth="4" nType="0" pos="l" purity="0.0000000000000000e+00" res="0.0000000000000000e+00" rms="0.0000000000000000e+00">
                <Node Cut="0.0000000000000000e+00" IVar="-1" NCoef="0" cType="1" depth="5" nType="-99" pos="l" purity="0.0000000000000000e+00" res="-1.1564271524548531e-02" rms="1.3460301160812378e+00" />
                <Node Cut="0.0000000000000000e+00" IVar="-1" NCoef="0" cType="1" depth="5" nType="-99" pos="r" purity="0.0000000000000000e+00" res="6.5310685895383358e-03" rms="7.3948651552200317e-01" />
              </Node>
              <Node Cut="9.0000000000000000e+00" IVar="2" NCoef="0" cType="1" depth="4" nType="0" pos="r" purity="0.0000000000000000e+00" res="0.0000000000000000e+00" rms="0.0000000000000000e+00">
                <Node Cut="0.0000000000000000e+00" IVar="-1" NCoef="0" cType="1" depth="5" nType="-99" pos="l" purity="0.0000000000000000e+00" res="2.9347606468945742e-03" rms="9.8104494810104370e-01" />
                <Node Cut="0.0000000000000000e+00" IVar="-1" NCoef="0" cType="1" depth="5" nType="-99" pos="r" purity="0.0000000000000000e+00" res="-5.9565787523752078e-05" rms="4.1090378165245056e-01" />
              </Node>
            </Node>
          </Node>
          <Node Cut="2.2500000000000000e+02" IVar="2" NCoef="0" cType="1" depth="2" nType="0" pos="r" purity="0.0000000000000000e+00" res="0.0000000000000000e+00" rms="0.0000000000000000e+00">
            <Node Cut="2.0000000000000000e+00" IVar="7" NCoef="0" cType="1" depth="3" nType="0" pos="l" purity="0.0000000000000000e+00" res="1.0145957348868251e-03" rms="4.0192344784736633e-01">
              <Node Cut="9.0000000000000000e+00" IVar="0" NCoef="0" cType="1" depth="4" nType="0" pos="l" purity="0.0000000000000000e+00" res="-2.1509162615984678e-03" rms="2.1560025215148926e-01">
                <Node Cut="0.0000000000000000e+00" IVar="-1" NCoef="0" cType="1" depth="5" nType="-99" pos="l" purity="0.0000000000000000e+00" res="-4.1435364983044565e-04" rms="2.2198161482810974e-01" />
                <Node Cut="0.0000000000000000e+00" IVar="-1" NCoef="0" cType="1" depth="5" nType="-99" pos="r" purity="0.0000000000000000e+00" res="5.2055949345231056e-04" rms="1.9001473486423492e-01" />
              </Node>
              <Node Cut="8.0000000000000000e+00" IVar="0" NCoef="0" cType="1" depth="4" nType="0" pos="r" purity="0.0000000000000000e+00" res="3.0173182021826506e-03" rms="4.8352313041687012e-01">
                <Node Cut="0.0000000000000000e+00" IVar="-1" NCoef="0" cType="1" depth="5" nType="-99" pos="l" purity="0.0000000000000000e+00" res="1.0627626907080412e-03" rms="4.0830734372138977e-01" />
                <Node Cut="0.0000000000000000e+00" IVar="-1" NCoef="0" cType="1" depth="5" nType="-99" pos="r" purity="0.0000000000000000e+00" res="-6.0377635236363858e-05" rms="5.1543325185775757e-01" />
              </Node>
            </Node>
            <Node Cut="1.0000000000000000e+00" IVar="7" NCoef="0" cType="1" depth="3" nType="0" pos="r" purity="0.0000000000000000e+00" res="-1.2248880229890347e-03" rms="2.1040871739387512e-01">
              <Node Cut="-2.0000000000000000e+00" IVar="6" NCoef="0" cType="1" depth="4" nType="0" pos="l" purity="0.0000000000000000e+00" res="3.6887347232550383e-03" rms="1.7410685122013092e-01">
                <Node Cut="0.0000000000000000e+00" IVar="-1" NCoef="0" cType="1" depth="5" nType="-99" pos="l" purity="0.0000000000000000e+00" res="-1.3083377853035927e-03" rms="1.4362657070159912e-01" />
                <Node Cut="0.0000000000000000e+00" IVar="-1" NCoef="0" cType="1" depth="5" nType="-99" pos="r" purity="0.0000000000000000e+00" res="4.9376388778910041e-04" rms="1.7725588381290436e-01" />
              </Node>
              <Node Cut="-1.0000000000000000e+00" IVar="5" NCoef="0" cType="1" depth="4" nType="0" pos="r" purity="0.0000000000000000e+00" res="-3.4874645061790943e-03" rms="2.2604596614837646e-01">
                <Node Cut="0.0000000000000000e+00" IVar="-1" NCoef="0" cType="1" depth="5" nType="-99" pos="l" purity="0.0000000000000000e+00" res="1.8620060291141272e-04" rms="1.7559140920639038e-01" />
                <Node Cut="0.0000000000000000e+00" IVar="-1" NCoef="0" cType="1" depth="5" nType="-99" pos="r" purity="0.0000000000000000e+00" res="-6.6437228815630078e-04" rms="2.5168314576148987e-01" />
              </Node>
            </Node>
          </Node>
        </Node>
        <Node Cut="3.0000000000000000e+00" IVar="0" NCoef="0" cType="1" depth="1" nType="0" pos="r" purity="0.0000000000000000e+00" res="2.4593560956418514e-03" rms="3.4730574488639832e-01">
          <Node Cut="1.8000000000000000e+01" IVar="2" NCoef="0" cType="1" depth="2" nType="0" pos="l" purity="0.0000000000000000e+00" res="0.0000000000000000e+00" rms="0.0000000000000000e+00">
            <Node Cut="0.0000000000000000e+00" IVar="5" NCoef="0" cType="1" depth="3" nType="0" pos="l" purity="0.0000000000000000e+00" res="0.0000000000000000e+00" rms="0.0000000000000000e+00">
              <Node Cut="1.4000000000000000e+01" IVar="2" NCoef="0" cType="1" depth="4" nType="0" pos="l" purity="0.0000000000000000e+00" res="1.0004032403230667e-01" rms="-nan">
                <Node Cut="0.0000000000000000e+00" IVar="-1" NCoef="0" cType="1" depth="5" nType="-99" pos="l" purity="0.0000000000000000e+00" res="1.6455797478556633e-02" rms="3.1961530447006226e-01" />
                <Node Cut="0.0000000000000000e+00" IVar="-1" NCoef="0" cType="1" depth="5" nType="-99" pos="r" purity="0.0000000000000000e+00" res="-2.9595186933875084e-02" rms="0.0000000000000000e+00" />
              </Node>
              <Node Cut="0.0000000000000000e+00" IVar="6" NCoef="0" cType="1" depth="4" nType="0" pos="r" purity="0.0000000000000000e+00" res="0.0000000000000000e+00" rms="0.0000000000000000e+00">
                <Node Cut="0.0000000000000000e+00" IVar="-1" NCoef="0" cType="1" depth="5" nType="-99" pos="l" purity="0.0000000000000000e+00" res="4.9768453463912010e-03" rms="4.4365137815475464e-01" />
                <Node Cut="0.0000000000000000e+00" IVar="-1" NCoef="0" cType="1" depth="5" nType="-99" pos="r" purity="0.0000000000000000e+00" res="-7.8652888536453247e-02" rms="7.1315610408782959e-01" />
              </Node>
            </Node>
            <Node Cut="4.5000000000000000e+01" IVar="2" NCoef="0" cType="1" depth="3" nType="0" pos="r" purity="0.0000000000000000e+00" res="0.0000000000000000e+00" rms="0.0000000000000000e+00">
              <Node Cut="1.0000000000000000e+00" IVar="3" NCoef="0" cType="1" depth="4" nType="0" pos="l" purity="0.0000000000000000e+00" res="1.6045109927654266e-01" rms="4.8633718490600586e-01">
                <Node Cut="0.0000000000000000e+00" IVar="-1" NCoef="0" cType="1" depth="5" nType="-99" pos="l" purity="0.0000000000000000e+00" res="2.8041014447808266e-02" rms="4.4436544179916382e-01" />
                <Node Cut="0.0000000000000000e+00" IVar="-1" NCoef="0" cType="1" depth="5" nType="-99" pos="r" purity="0.0000000000000000e+00" res="-5.7487734593451023e-03" rms="4.8358234763145447e-01" />
              </Node>
              <Node Cut="2.0000000000000000e+00" IVar="0" NCoef="0" cType="1" depth="4" nType="0" pos="r" purity="0.0000000000000000e+00" res="1.4858970418572426e-02" rms="3.2751327753067017e-01">
                <Node Cut="0.0000000000000000e+00" IVar="-1" NCoef="0" cType="1" depth="5" nType="-99" pos="l" purity="0.0000000000000000e+00" res="-2.5887829251587391e-03" rms="3.8971245288848877e-01" />
                <Node Cut="0.0000000000000000e+00" IVar="-1" NCoef="0" cType="1" depth="5" nType="-99" pos="r" purity="0.0000000000000000e+00" res="2.6391777209937572e-03" rms="3.0665218830108643e-01" />
              </Node>
            </Node>
          </Node>
          <Node Cut="1.0000000000000000e+00" IVar="3" NCoef="0" cType="1" depth="2" nType="0" pos="r" purity="0.0000000000000000e+00" res="4.4296961277723312e-05" rms="1.8421566486358643e-01">
            <Node Cut="-2.0000000000000000e+00" IVar="6" NCoef="0" cType="1" depth="3" nType="0" pos="l" purity="0.0000000000000000e+00" res="1.0064864531159401e-02" rms="3.8717421889305115e-01">
              <Node Cut="0.0000000000000000e+00" IVar="5" NCoef="0" cType="1" depth="4" nType="0" pos="l" purity="0.0000000000000000e+00" res="-2.2250516340136528e-02" rms="2.3541407287120819e-01">
                <Node Cut="0.0000000000000000e+00" IVar="-1" NCoef="0" cType="1" depth="5" nType="-99" pos="l" purity="0.0000000000000000e+00" res="1.1259057372808456e-01" rms="8.9242184162139893e-01" />
                <Node Cut="0.0000000000000000e+00" IVar="-1" NCoef="0" cType="1" depth="5" nType="-99" pos="r" purity="0.0000000000000000e+00" res="-2.8236859943717718e-03" rms="2.2323888540267944e-01" />
              </Node>
              <Node Cut="1.0000000000000000e+00" IVar="2" NCoef="0" cType="1" depth="4" nType="0" pos="r" purity="0.0000000000000000e+00" res="0.0000000000000000e+00" rms="0.0000000000000000e+00">
                <Node Cut="0.0000000000000000e+00" IVar="-1" NCoef="0" cType="1" depth="5" nType="-99" pos="l" purity="0.0000000000000000e+00" res="3.4511688351631165e-01" rms="3.5436043143272400e-01" />
                <Node Cut="0.0000000000000000e+00" IVar="-1" NCoef="0" cType="1" depth="5" nType="-99" pos="r" purity="0.0000000000000000e+00" res="1.7920829122886062e-03" rms="4.1479972004890442e-01" />
              </Node>
            </Node>
            <Node Cut="1.0000000000000000e+01" IVar="2" NCoef="0" cType="1" depth="3" nType="0" pos="r" purity="0.0000000000000000e+00" res="0.0000000000000000e+00" rms="0.0000000000000000e+00">
              <Node Cut="7.0000000000000000e+00" IVar="2" NCoef="0" cType="1" depth="4" nType="0" pos="l" purity="0.0000000000000000e+00" res="9.1320760548114777e-02" rms="4.5626208186149597e-01">
                <Node Cut="0.0000000000000000e+00" IVar="-1" NCoef="0" cType="1" depth="5" nType="-99" pos="l" purity="0.0000000000000000e+00" res="-4.9120807088911533e-03" rms="5.0267857313156128e-01" />
                <Node Cut="0.0000000000000000e+00" IVar="-1" NCoef="0" cType="1" depth="5" nType="-99" pos="r" purity="0.0000000000000000e+00" res="2.5349713861942291e-02" rms="3.3635565638542175e-01" />
              </Node>
              <Node Cut="2.1500000000000000e+02" IVar="2" NCoef="0" cType="1" depth="4" nType="0" pos="r" purity="0.0000000000000000e+00" res="0.0000000000000000e+00" rms="0.0000000000000000e+00">
                <Node Cut="0.0000000000000000e+00" IVar="-1" NCoef="0" cType="1" depth="5" nType="-99" pos="l" purity="0.0000000000000000e+00" res="-2.6118834502995014e-03" rms="3.5217988491058350e-01" />
                <Node Cut="0.0000000000000000e+00" IVar="-1" NCoef="0" cType="1" depth="5" nType="-99" pos="r" purity="0.0000000000000000e+00" res="-1.5719310613349080e-04" rms="2.1773461997509003e-01" />
              </Node>
            </Node>
          </Node>
        </Node>
      </Node>
    </BinaryTree>
    