<?xml version="1.0"?>
<BinaryTree boostWeight="1.0000000000000000e+00" itree="202" type="DecisionTree">
      <Node Cut="1.4000000000000000e+01" IVar="0" NCoef="0" cType="1" depth="0" nType="0" pos="s" purity="0.0000000000000000e+00" res="1.1336868943612188e-10" rms="1.3514472544193268e-01">
        <Node Cut="0.0000000000000000e+00" IVar="6" NCoef="0" cType="1" depth="1" nType="0" pos="l" purity="0.0000000000000000e+00" res="-1.1249289382249117e-03" rms="1.2772241234779358e-01">
          <Node Cut="2.7000000000000000e+01" IVar="1" NCoef="0" cType="1" depth="2" nType="0" pos="l" purity="0.0000000000000000e+00" res="1.2386450767517090e+00" rms="-nan">
            <Node Cut="1.3000000000000000e+01" IVar="0" NCoef="0" cType="1" depth="3" nType="0" pos="l" purity="0.0000000000000000e+00" res="2.1992320194840431e-02" rms="1.5669199824333191e-01">
              <Node Cut="1.0000000000000000e+00" IVar="4" NCoef="0" cType="1" depth="4" nType="0" pos="l" purity="0.0000000000000000e+00" res="2.0765040069818497e-02" rms="1.0858782380819321e-01">
                <Node Cut="0.0000000000000000e+00" IVar="-1" NCoef="0" cType="1" depth="5" nType="-99" pos="l" purity="0.0000000000000000e+00" res="1.0114742908626795e-03" rms="1.3044720888137817e-01" />
                <Node Cut="0.0000000000000000e+00" IVar="-1" NCoef="0" cType="1" depth="5" nType="-99" pos="r" purity="0.0000000000000000e+00" res="2.4376081302762032e-02" rms="0.0000000000000000e+00" />
              </Node>
              <Node Cut="1.0000000000000000e+00" IVar="2" NCoef="0" cType="1" depth="4" nType="0" pos="r" purity="0.0000000000000000e+00" res="0.0000000000000000e+00" rms="0.0000000000000000e+00">
                <Node Cut="0.0000000000000000e+00" IVar="-1" NCoef="0" cType="1" depth="5" nType="-99" pos="l" purity="0.0000000000000000e+00" res="9.1872647404670715e-02" rms="0.0000000000000000e+00" />
                <Node Cut="0.0000000000000000e+00" IVar="-1" NCoef="0" cType="1" depth="5" nType="-99" pos="r" purity="0.0000000000000000e+00" res="-8.0597994383424520e-04" rms="2.1274957805871964e-02" />
              </Node>
            </Node>
            <Node Cut="6.3000000000000000e+01" IVar="1" NCoef="0" cType="1" depth="3" nType="0" pos="r" purity="0.0000000000000000e+00" res="0.0000000000000000e+00" rms="0.0000000000000000e+00">
              <Node Cut="-2.0000000000000000e+00" IVar="6" NCoef="0" cType="1" depth="4" nType="0" pos="l" purity="0.0000000000000000e+00" res="-2.9660280793905258e-02" rms="6.2208350747823715e-02">
                <Node Cut="0.0000000000000000e+00" IVar="-1" NCoef="0" cType="1" depth="5" nType="-99" pos="l" purity="0.0000000000000000e+00" res="2.5028116069734097e-03" rms="3.4853316843509674e-02" />
                <Node Cut="0.0000000000000000e+00" IVar="-1" NCoef="0" cType="1" depth="5" nType="-99" pos="r" purity="0.0000000000000000e+00" res="-6.6111092455685139e-03" rms="8.5221529006958008e-02" />
              </Node>
              <Node Cut="1.0700000000000000e+02" IVar="1" NCoef="0" cType="1" depth="4" nType="0" pos="r" purity="0.0000000000000000e+00" res="0.0000000000000000e+00" rms="0.0000000000000000e+00">
                <Node Cut="0.0000000000000000e+00" IVar="-1" NCoef="0" cType="1" depth="5" nType="-99" pos="l" purity="0.0000000000000000e+00" res="1.8500486621633172e-03" rms="9.9312387406826019e-02" />
                <Node Cut="0.0000000000000000e+00" IVar="-1" NCoef="0" cType="1" depth="5" nType="-99" pos="r" purity="0.0000000000000000e+00" res="-2.5058528990484774e-04" rms="9.3992576003074646e-02" />
              </Node>
            </Node>
          </Node>
          <Node Cut="1.1000000000000000e+01" IVar="0" NCoef="0" cType="1" depth="2" nType="0" pos="r" purity="0.0000000000000000e+00" res="-8.8729690760374069e-03" rms="1.8615244328975677e-01">
            <Node Cut="9.0000000000000000e+00" IVar="1" NCoef="0" cType="1" depth="3" nType="0" pos="l" purity="0.0000000000000000e+00" res="0.0000000000000000e+00" rms="0.0000000000000000e+00">
              <Node Cut="7.0000000000000000e+00" IVar="1" NCoef="0" cType="1" depth="4" nType="0" pos="l" purity="0.0000000000000000e+00" res="2.6719826459884644e-01" rms="-nan">
                <Node Cut="0.0000000000000000e+00" IVar="-1" NCoef="0" cType="1" depth="5" nType="-99" pos="l" purity="0.0000000000000000e+00" res="1.1595387477427721e-03" rms="4.4449883699417114e-01" />
                <Node Cut="0.0000000000000000e+00" IVar="-1" NCoef="0" cType="1" depth="5" nType="-99" pos="r" purity="0.0000000000000000e+00" res="-1.5632616356015205e-02" rms="5.3003419190645218e-02" />
              </Node>
              <Node Cut="1.5000000000000000e+01" IVar="1" NCoef="0" cType="1" depth="4" nType="0" pos="r" purity="0.0000000000000000e+00" res="5.2500110864639282e-01" rms="6.1267870664596558e-01">
                <Node Cut="0.0000000000000000e+00" IVar="-1" NCoef="0" cType="1" depth="5" nType="-99" pos="l" purity="0.0000000000000000e+00" res="8.6088469251990318e-03" rms="5.1350656896829605e-02" />
                <Node Cut="0.0000000000000000e+00" IVar="-1" NCoef="0" cType="1" depth="5" nType="-99" pos="r" purity="0.0000000000000000e+00" res="-1.1888016015291214e-03" rms="1.0000067204236984e-01" />
              </Node>
            </Node>
            <Node Cut="1.0000000000000000e+00" IVar="1" NCoef="0" cType="1" depth="3" nType="0" pos="r" purity="0.0000000000000000e+00" res="0.0000000000000000e+00" rms="0.0000000000000000e+00">
              <Node Cut="0.0000000000000000e+00" IVar="-1" NCoef="0" cType="1" depth="4" nType="-99" pos="l" purity="0.0000000000000000e+00" res="3.9634066820144653e-01" rms="0.0000000000000000e+00" />
              <Node Cut="7.1000000000000000e+01" IVar="1" NCoef="0" cType="1" depth="4" nType="0" pos="r" purity="0.0000000000000000e+00" res="0.0000000000000000e+00" rms="0.0000000000000000e+00">
                <Node Cut="0.0000000000000000e+00" IVar="-1" NCoef="0" cType="1" depth="5" nType="-99" pos="l" purity="0.0000000000000000e+00" res="5.0425282679498196e-03" rms="2.6432007551193237e-01" />
                <Node Cut="0.0000000000000000e+00" IVar="-1" NCoef="0" cType="1" depth="5" nType="-99" pos="r" purity="0.0000000000000000e+00" res="-1.3733863597735763e-03" rms="1.2894745171070099e-01" />
              </Node>
            </Node>
          </Node>
        </Node>
        <Node Cut="1.7000000000000000e+01" IVar="0" NCoef="0" cType="1" depth="1" nType="0" pos="r" purity="0.0000000000000000e+00" res="2.7199942269362509e-04" rms="1.3447633385658264e-01">
          <Node Cut="1.3500000000000000e+02" IVar="1" NCoef="0" cType="1" depth="2" nType="0" pos="l" purity="0.0000000000000000e+00" res="0.0000000000000000e+00" rms="0.0000000000000000e+00">
            <Node Cut="0.0000000000000000e+00" IVar="6" NCoef="0" cType="1" depth="3" nType="0" pos="l" purity="0.0000000000000000e+00" res="2.0332610234618187e-02" rms="-nan">
              <Node Cut="1.0300000000000000e+02" IVar="1" NCoef="0" cType="1" depth="4" nType="0" pos="l" purity="0.0000000000000000e+00" res="0.0000000000000000e+00" rms="6.0355776548385620e-01">
                <Node Cut="0.0000000000000000e+00" IVar="-1" NCoef="0" cType="1" depth="5" nType="-99" pos="l" purity="0.0000000000000000e+00" res="-9.8856736440211535e-04" rms="6.1041995882987976e-02" />
                <Node Cut="0.0000000000000000e+00" IVar="-1" NCoef="0" cType="1" depth="5" nType="-99" pos="r" purity="0.0000000000000000e+00" res="-5.8538708835840225e-03" rms="6.5414354205131531e-02" />
              </Node>
              <Node Cut="1.0000000000000000e+00" IVar="1" NCoef="0" cType="1" depth="4" nType="0" pos="r" purity="0.0000000000000000e+00" res="1.6605986654758453e-01" rms="5.7348371093750000e+04">
                <Node Cut="0.0000000000000000e+00" IVar="-1" NCoef="0" cType="1" depth="5" nType="-99" pos="l" purity="0.0000000000000000e+00" res="3.9356070756912231e-01" rms="3.7782979011535645e-01" />
                <Node Cut="0.0000000000000000e+00" IVar="-1" NCoef="0" cType="1" depth="5" nType="-99" pos="r" purity="0.0000000000000000e+00" res="3.0471442732959986e-03" rms="1.6910021007061005e-01" />
              </Node>
            </Node>
            <Node Cut="1.5300000000000000e+02" IVar="1" NCoef="0" cType="1" depth="3" nType="0" pos="r" purity="0.0000000000000000e+00" res="7.3021636009216309e+00" rms="-nan">
              <Node Cut="1.4500000000000000e+02" IVar="1" NCoef="0" cType="1" depth="4" nType="0" pos="l" purity="0.0000000000000000e+00" res="9.6941227093338966e-04" rms="1.4944982528686523e+00">
                <Node Cut="0.0000000000000000e+00" IVar="-1" NCoef="0" cType="1" depth="5" nType="-99" pos="l" purity="0.0000000000000000e+00" res="2.9689639341086149e-03" rms="1.0714187473058701e-01" />
                <Node Cut="0.0000000000000000e+00" IVar="-1" NCoef="0" cType="1" depth="5" nType="-99" pos="r" purity="0.0000000000000000e+00" res="3.9436154067516327e-02" rms="7.7041554450988770e-01" />
              </Node>
              <Node Cut="1.0000000000000000e+00" IVar="2" NCoef="0" cType="1" depth="4" nType="0" pos="r" purity="0.0000000000000000e+00" res="1.3829702511429787e-02" rms="7.2383306920528412e-02">
                <Node Cut="0.0000000000000000e+00" IVar="-1" NCoef="0" cType="1" depth="5" nType="-99" pos="l" purity="0.0000000000000000e+00" res="-2.2450513206422329e-03" rms="5.4681632667779922e-02" />
                <Node Cut="0.0000000000000000e+00" IVar="-1" NCoef="0" cType="1" depth="5" nType="-99" pos="r" purity="0.0000000000000000e+00" res="6.5368609502911568e-03" rms="9.4150014221668243e-02" />
              </Node>
            </Node>
          </Node>
          <Node Cut="2.7000000000000000e+01" IVar="1" NCoef="0" cType="1" depth="2" nType="0" pos="r" purity="0.0000000000000000e+00" res="9.8855518444906920e-05" rms="-nan">
            <Node Cut="2.0000000000000000e+01" IVar="0" NCoef="0" cType="1" depth="3" nType="0" pos="l" purity="0.0000000000000000e+00" res="-4.8365076072514057e-03" rms="2.3408047854900360e-01">
              <Node Cut="1.1000000000000000e+01" IVar="1" NCoef="0" cType="1" depth="4" nType="0" pos="l" purity="0.0000000000000000e+00" res="0.0000000000000000e+00" rms="0.0000000000000000e+00">
                <Node Cut="0.0000000000000000e+00" IVar="-1" NCoef="0" cType="1" depth="5" nType="-99" pos="l" purity="0.0000000000000000e+00" res="-7.0471636718139052e-04" rms="1.3647711277008057e-01" />
                <Node Cut="0.0000000000000000e+00" IVar="-1" NCoef="0" cType="1" depth="5" nType="-99" pos="r" purity="0.0000000000000000e+00" res="-4.0941322222352028e-03" rms="6.7351244390010834e-02" />
              </Node>
              <Node Cut="2.3000000000000000e+01" IVar="0" NCoef="0" cType="1" depth="4" nType="0" pos="r" purity="0.0000000000000000e+00" res="3.3692256547510624e-03" rms="2.7739474177360535e-01">
                <Node Cut="0.0000000000000000e+00" IVar="-1" NCoef="0" cType="1" depth="5" nType="-99" pos="l" purity="0.0000000000000000e+00" res="2.2236511576920748e-03" rms="3.5117036104202271e-01" />
                <Node Cut="0.0000000000000000e+00" IVar="-1" NCoef="0" cType="1" depth="5" nType="-99" pos="r" purity="0.0000000000000000e+00" res="-1.1291655246168375e-03" rms="2.0105268061161041e-01" />
              </Node>
            </Node>
            <Node Cut="2.8000000000000000e+01" IVar="1" NCoef="0" cType="1" depth="3" nType="0" pos="r" purity="0.0000000000000000e+00" res="0.0000000000000000e+00" rms="0.0000000000000000e+00">
              <Node Cut="0.0000000000000000e+00" IVar="-1" NCoef="0" cType="1" depth="4" nType="-99" pos="l" purity="0.0000000000000000e+00" res="5.1270272582769394e-02" rms="0.0000000000000000e+00" />
              <Node Cut="4.4000000000000000e+01" IVar="1" NCoef="0" cType="1" depth="4" nType="0" pos="r" purity="0.0000000000000000e+00" res="0.0000000000000000e+00" rms="0.0000000000000000e+00">
                <Node Cut="0.0000000000000000e+00" IVar="-1" NCoef="0" cType="1" depth="5" nType="-99" pos="l" purity="0.0000000000000000e+00" res="1.4783400110900402e-03" rms="1.3928715884685516e-01" />
                <Node Cut="0.0000000000000000e+00" IVar="-1" NCoef="0" cType="1" depth="5" nType="-99" pos="r" purity="0.0000000000000000e+00" res="1.7784245756047312e-06" rms="1.1260683834552765e-01" />
              </Node>
            </Node>
          </Node>
        </Node>
      </Node>
    </BinaryTree>
    