<?xml version="1.0"?>
<BinaryTree boostWeight="1.0000000000000000e+00" itree="388" type="DecisionTree">
      <Node Cut="1.0000000000000000e+00" IVar="3" NCoef="0" cType="1" depth="0" nType="0" pos="s" purity="0.0000000000000000e+00" res="-1.5642333892174065e-05" rms="6.2977813184261322e-02">
        <Node Cut="6.0000000000000000e+00" IVar="0" NCoef="0" cType="1" depth="1" nType="0" pos="l" purity="0.0000000000000000e+00" res="6.7800247052218765e-05" rms="1.4937727153301239e-01">
          <Node Cut="2.2500000000000000e+02" IVar="1" NCoef="0" cType="1" depth="2" nType="0" pos="l" purity="0.0000000000000000e+00" res="0.0000000000000000e+00" rms="0.0000000000000000e+00">
            <Node Cut="4.0000000000000000e+00" IVar="5" NCoef="0" cType="1" depth="3" nType="0" pos="l" purity="0.0000000000000000e+00" res="0.0000000000000000e+00" rms="-nan">
              <Node Cut="-3.0000000000000000e+00" IVar="5" NCoef="0" cType="1" depth="4" nType="0" pos="l" purity="0.0000000000000000e+00" res="8.4269018843770027e-03" rms="-nan">
                <Node Cut="0.0000000000000000e+00" IVar="-1" NCoef="0" cType="1" depth="5" nType="-99" pos="l" purity="0.0000000000000000e+00" res="4.1886437684297562e-03" rms="9.2313379049301147e-02" />
                <Node Cut="0.0000000000000000e+00" IVar="-1" NCoef="0" cType="1" depth="5" nType="-99" pos="r" purity="0.0000000000000000e+00" res="-3.6928938698110869e-06" rms="1.6769798099994659e-01" />
              </Node>
              <Node Cut="3.0000000000000000e+00" IVar="0" NCoef="0" cType="1" depth="4" nType="0" pos="r" purity="0.0000000000000000e+00" res="7.6349571347236633e-02" rms="1.1287569254636765e-01">
                <Node Cut="0.0000000000000000e+00" IVar="-1" NCoef="0" cType="1" depth="5" nType="-99" pos="l" purity="0.0000000000000000e+00" res="-2.2382263559848070e-03" rms="3.3641103655099869e-02" />
                <Node Cut="0.0000000000000000e+00" IVar="-1" NCoef="0" cType="1" depth="5" nType="-99" pos="r" purity="0.0000000000000000e+00" res="1.3411408290266991e-02" rms="1.0243593156337738e-01" />
              </Node>
            </Node>
            <Node Cut="4.0000000000000000e+00" IVar="5" NCoef="0" cType="1" depth="3" nType="0" pos="r" purity="0.0000000000000000e+00" res="7.1932114660739899e-03" rms="-nan">
              <Node Cut="1.0000000000000000e+00" IVar="4" NCoef="0" cType="1" depth="4" nType="0" pos="l" purity="0.0000000000000000e+00" res="6.9701373577117920e-03" rms="-nan">
                <Node Cut="0.0000000000000000e+00" IVar="-1" NCoef="0" cType="1" depth="5" nType="-99" pos="l" purity="0.0000000000000000e+00" res="-2.9478731448762119e-04" rms="1.2037773430347443e-01" />
                <Node Cut="0.0000000000000000e+00" IVar="-1" NCoef="0" cType="1" depth="5" nType="-99" pos="r" purity="0.0000000000000000e+00" res="2.0983927242923528e-04" rms="1.3318532705307007e-01" />
              </Node>
              <Node Cut="6.0000000000000000e+00" IVar="6" NCoef="0" cType="1" depth="4" nType="0" pos="r" purity="0.0000000000000000e+00" res="4.4315154664218426e-03" rms="-nan">
                <Node Cut="0.0000000000000000e+00" IVar="-1" NCoef="0" cType="1" depth="5" nType="-99" pos="l" purity="0.0000000000000000e+00" res="-3.1790391076356173e-03" rms="1.8767486512660980e-01" />
                <Node Cut="0.0000000000000000e+00" IVar="-1" NCoef="0" cType="1" depth="5" nType="-99" pos="r" purity="0.0000000000000000e+00" res="1.7155336216092110e-02" rms="1.2739098072052002e-01" />
              </Node>
            </Node>
          </Node>
          <Node Cut="2.2500000000000000e+02" IVar="1" NCoef="0" cType="1" depth="2" nType="0" pos="r" purity="0.0000000000000000e+00" res="0.0000000000000000e+00" rms="0.0000000000000000e+00">
            <Node Cut="5.0000000000000000e+00" IVar="6" NCoef="0" cType="1" depth="3" nType="0" pos="l" purity="0.0000000000000000e+00" res="2.6398047339171171e-05" rms="1.3629937171936035e-01">
              <Node Cut="1.7500000000000000e+02" IVar="1" NCoef="0" cType="1" depth="4" nType="0" pos="l" purity="0.0000000000000000e+00" res="0.0000000000000000e+00" rms="0.0000000000000000e+00">
                <Node Cut="0.0000000000000000e+00" IVar="-1" NCoef="0" cType="1" depth="5" nType="-99" pos="l" purity="0.0000000000000000e+00" res="1.6127972048707306e-04" rms="1.4254002273082733e-01" />
                <Node Cut="0.0000000000000000e+00" IVar="-1" NCoef="0" cType="1" depth="5" nType="-99" pos="r" purity="0.0000000000000000e+00" res="-2.0171333744656295e-04" rms="1.2426434457302094e-01" />
              </Node>
              <Node Cut="0.0000000000000000e+00" IVar="4" NCoef="0" cType="1" depth="4" nType="0" pos="r" purity="0.0000000000000000e+00" res="0.0000000000000000e+00" rms="0.0000000000000000e+00">
                <Node Cut="0.0000000000000000e+00" IVar="-1" NCoef="0" cType="1" depth="5" nType="-99" pos="l" purity="0.0000000000000000e+00" res="-1.2927780626341701e-03" rms="1.3148260116577148e-01" />
                <Node Cut="0.0000000000000000e+00" IVar="-1" NCoef="0" cType="1" depth="5" nType="-99" pos="r" purity="0.0000000000000000e+00" res="1.0614907369017601e-03" rms="1.1886631697416306e-01" />
              </Node>
            </Node>
            <Node Cut="3.0000000000000000e+00" IVar="5" NCoef="0" cType="1" depth="3" nType="0" pos="r" purity="0.0000000000000000e+00" res="0.0000000000000000e+00" rms="0.0000000000000000e+00">
              <Node Cut="7.0000000000000000e+00" IVar="0" NCoef="0" cType="1" depth="4" nType="0" pos="l" purity="0.0000000000000000e+00" res="3.8988399319350719e-03" rms="1.2602567672729492e-01">
                <Node Cut="0.0000000000000000e+00" IVar="-1" NCoef="0" cType="1" depth="5" nType="-99" pos="l" purity="0.0000000000000000e+00" res="7.8378082253038883e-04" rms="1.3344648480415344e-01" />
                <Node Cut="0.0000000000000000e+00" IVar="-1" NCoef="0" cType="1" depth="5" nType="-99" pos="r" purity="0.0000000000000000e+00" res="1.5239817730616778e-04" rms="1.2127065658569336e-01" />
              </Node>
              <Node Cut="3.0000000000000000e+00" IVar="6" NCoef="0" cType="1" depth="4" nType="0" pos="r" purity="0.0000000000000000e+00" res="-6.2058749608695507e-03" rms="1.0811942070722580e-01">
                <Node Cut="0.0000000000000000e+00" IVar="-1" NCoef="0" cType="1" depth="5" nType="-99" pos="l" purity="0.0000000000000000e+00" res="-1.5384186990559101e-03" rms="9.9599599838256836e-02" />
                <Node Cut="0.0000000000000000e+00" IVar="-1" NCoef="0" cType="1" depth="5" nType="-99" pos="r" purity="0.0000000000000000e+00" res="7.9703731898916885e-06" rms="1.1325813084840775e-01" />
              </Node>
            </Node>
          </Node>
        </Node>
        <Node Cut="9.0000000000000000e+00" IVar="1" NCoef="0" cType="1" depth="1" nType="0" pos="r" purity="0.0000000000000000e+00" res="0.0000000000000000e+00" rms="0.0000000000000000e+00">
          <Node Cut="1.0000000000000000e+00" IVar="4" NCoef="0" cType="1" depth="2" nType="0" pos="l" purity="0.0000000000000000e+00" res="0.0000000000000000e+00" rms="0.0000000000000000e+00">
            <Node Cut="5.0000000000000000e+00" IVar="0" NCoef="0" cType="1" depth="3" nType="0" pos="l" purity="0.0000000000000000e+00" res="9.3329238006845117e-04" rms="4.0587434172630310e-01">
              <Node Cut="0.0000000000000000e+00" IVar="5" NCoef="0" cType="1" depth="4" nType="0" pos="l" purity="0.0000000000000000e+00" res="3.2392551656812429e-03" rms="2.3415039479732513e-01">
                <Node Cut="0.0000000000000000e+00" IVar="-1" NCoef="0" cType="1" depth="5" nType="-99" pos="l" purity="0.0000000000000000e+00" res="-3.3950847573578358e-03" rms="2.3850110173225403e-01" />
                <Node Cut="0.0000000000000000e+00" IVar="-1" NCoef="0" cType="1" depth="5" nType="-99" pos="r" purity="0.0000000000000000e+00" res="1.0566812707111239e-03" rms="3.6270937323570251e-01" />
              </Node>
              <Node Cut="4.0000000000000000e+00" IVar="6" NCoef="0" cType="1" depth="4" nType="0" pos="r" purity="0.0000000000000000e+00" res="-1.0897002182900906e-02" rms="5.1128530502319336e-01">
                <Node Cut="0.0000000000000000e+00" IVar="-1" NCoef="0" cType="1" depth="5" nType="-99" pos="l" purity="0.0000000000000000e+00" res="-2.8029091190546751e-03" rms="1.5904906392097473e-01" />
                <Node Cut="0.0000000000000000e+00" IVar="-1" NCoef="0" cType="1" depth="5" nType="-99" pos="r" purity="0.0000000000000000e+00" res="9.4023899873718619e-04" rms="7.3982185125350952e-01" />
              </Node>
            </Node>
            <Node Cut="3.0000000000000000e+00" IVar="1" NCoef="0" cType="1" depth="3" nType="0" pos="r" purity="0.0000000000000000e+00" res="4.9598798155784607e-02" rms="4.4333750009536743e-01">
              <Node Cut="3.0000000000000000e+00" IVar="6" NCoef="0" cType="1" depth="4" nType="0" pos="l" purity="0.0000000000000000e+00" res="-3.0495200771838427e-03" rms="3.6339980363845825e-01">
                <Node Cut="0.0000000000000000e+00" IVar="-1" NCoef="0" cType="1" depth="5" nType="-99" pos="l" purity="0.0000000000000000e+00" res="1.9998230040073395e-02" rms="0.0000000000000000e+00" />
                <Node Cut="0.0000000000000000e+00" IVar="-1" NCoef="0" cType="1" depth="5" nType="-99" pos="r" purity="0.0000000000000000e+00" res="-1.8678465858101845e-03" rms="3.8422539830207825e-01" />
              </Node>
              <Node Cut="5.0000000000000000e+00" IVar="0" NCoef="0" cType="1" depth="4" nType="0" pos="r" purity="0.0000000000000000e+00" res="1.9355708360671997e-01" rms="5.7314956188201904e-01">
                <Node Cut="0.0000000000000000e+00" IVar="-1" NCoef="0" cType="1" depth="5" nType="-99" pos="l" purity="0.0000000000000000e+00" res="1.4172367751598358e-02" rms="3.9344260096549988e-01" />
                <Node Cut="0.0000000000000000e+00" IVar="-1" NCoef="0" cType="1" depth="5" nType="-99" pos="r" purity="0.0000000000000000e+00" res="1.0020225495100021e-01" rms="1.5304561853408813e+00" />
              </Node>
            </Node>
          </Node>
          <Node Cut="2.2000000000000000e+01" IVar="1" NCoef="0" cType="1" depth="2" nType="0" pos="r" purity="0.0000000000000000e+00" res="0.0000000000000000e+00" rms="0.0000000000000000e+00">
            <Node Cut="3.0000000000000000e+00" IVar="0" NCoef="0" cType="1" depth="3" nType="0" pos="l" purity="0.0000000000000000e+00" res="-6.6242874599993229e-03" rms="2.1725460886955261e-01">
              <Node Cut="1.0000000000000000e+00" IVar="4" NCoef="0" cType="1" depth="4" nType="0" pos="l" purity="0.0000000000000000e+00" res="0.0000000000000000e+00" rms="0.0000000000000000e+00">
                <Node Cut="0.0000000000000000e+00" IVar="-1" NCoef="0" cType="1" depth="5" nType="-99" pos="l" purity="0.0000000000000000e+00" res="-4.4513423927128315e-03" rms="1.6257579624652863e-01" />
                <Node Cut="0.0000000000000000e+00" IVar="-1" NCoef="0" cType="1" depth="5" nType="-99" pos="r" purity="0.0000000000000000e+00" res="2.4316604249179363e-03" rms="1.9051197171211243e-01" />
              </Node>
              <Node Cut="0.0000000000000000e+00" IVar="4" NCoef="0" cType="1" depth="4" nType="0" pos="r" purity="0.0000000000000000e+00" res="1.4840022325515747e+00" rms="-nan">
                <Node Cut="0.0000000000000000e+00" IVar="-1" NCoef="0" cType="1" depth="5" nType="-99" pos="l" purity="0.0000000000000000e+00" res="3.4150367137044668e-03" rms="3.3158892393112183e-01" />
                <Node Cut="0.0000000000000000e+00" IVar="-1" NCoef="0" cType="1" depth="5" nType="-99" pos="r" purity="0.0000000000000000e+00" res="-2.6019604410976171e-04" rms="2.1265284717082977e-01" />
              </Node>
            </Node>
            <Node Cut="3.0000000000000000e+01" IVar="1" NCoef="0" cType="1" depth="3" nType="0" pos="r" purity="0.0000000000000000e+00" res="0.0000000000000000e+00" rms="0.0000000000000000e+00">
              <Node Cut="1.0000000000000000e+00" IVar="5" NCoef="0" cType="1" depth="4" nType="0" pos="l" purity="0.0000000000000000e+00" res="5.2411649376153946e-03" rms="1.7181265354156494e-01">
                <Node Cut="0.0000000000000000e+00" IVar="-1" NCoef="0" cType="1" depth="5" nType="-99" pos="l" purity="0.0000000000000000e+00" res="1.0694827651605010e-03" rms="2.0688439905643463e-01" />
                <Node Cut="0.0000000000000000e+00" IVar="-1" NCoef="0" cType="1" depth="5" nType="-99" pos="r" purity="0.0000000000000000e+00" res="-1.8848489271476865e-03" rms="1.5302515029907227e-01" />
              </Node>
              <Node Cut="3.9000000000000000e+01" IVar="1" NCoef="0" cType="1" depth="4" nType="0" pos="r" purity="0.0000000000000000e+00" res="0.0000000000000000e+00" rms="0.0000000000000000e+00">
                <Node Cut="0.0000000000000000e+00" IVar="-1" NCoef="0" cType="1" depth="5" nType="-99" pos="l" purity="0.0000000000000000e+00" res="-7.1955501334741712e-04" rms="1.8784666061401367e-01" />
                <Node Cut="0.0000000000000000e+00" IVar="-1" NCoef="0" cType="1" depth="5" nType="-99" pos="r" purity="0.0000000000000000e+00" res="-3.3771086691558594e-06" rms="1.3555867969989777e-01" />
              </Node>
            </Node>
          </Node>
        </Node>
      </Node>
    </BinaryTree>
    