<?xml version="1.0"?>
<BinaryTree boostWeight="1.0000000000000000e+00" itree="324" type="DecisionTree">
      <Node Cut="5.1000000000000000e+01" IVar="1" NCoef="0" cType="1" depth="0" nType="0" pos="s" purity="0.0000000000000000e+00" res="0.0000000000000000e+00" rms="0.0000000000000000e+00">
        <Node Cut="7.0000000000000000e+00" IVar="4" NCoef="0" cType="1" depth="1" nType="0" pos="l" purity="0.0000000000000000e+00" res="-5.1527738833101466e-05" rms="7.6522630453109741e-01">
          <Node Cut="2.0000000000000000e+00" IVar="6" NCoef="0" cType="1" depth="2" nType="0" pos="l" purity="0.0000000000000000e+00" res="3.0824550776742399e-05" rms="7.7165538072586060e-01">
            <Node Cut="7.0000000000000000e+00" IVar="0" NCoef="0" cType="1" depth="3" nType="0" pos="l" purity="0.0000000000000000e+00" res="-3.4384566824883223e-03" rms="8.3384394645690918e-01">
              <Node Cut="3.9000000000000000e+01" IVar="1" NCoef="0" cType="1" depth="4" nType="0" pos="l" purity="0.0000000000000000e+00" res="0.0000000000000000e+00" rms="0.0000000000000000e+00">
                <Node Cut="0.0000000000000000e+00" IVar="-1" NCoef="0" cType="1" depth="5" nType="-99" pos="l" purity="0.0000000000000000e+00" res="-1.0888088494539261e-02" rms="5.8344054222106934e-01" />
                <Node Cut="0.0000000000000000e+00" IVar="-1" NCoef="0" cType="1" depth="5" nType="-99" pos="r" purity="0.0000000000000000e+00" res="2.4459543055854738e-04" rms="2.6171243190765381e-01" />
              </Node>
              <Node Cut="1.2000000000000000e+01" IVar="0" NCoef="0" cType="1" depth="4" nType="0" pos="r" purity="0.0000000000000000e+00" res="-2.6238907594233751e-03" rms="8.3633124828338623e-01">
                <Node Cut="0.0000000000000000e+00" IVar="-1" NCoef="0" cType="1" depth="5" nType="-99" pos="l" purity="0.0000000000000000e+00" res="5.9312772937119007e-03" rms="8.2500964403152466e-01" />
                <Node Cut="0.0000000000000000e+00" IVar="-1" NCoef="0" cType="1" depth="5" nType="-99" pos="r" purity="0.0000000000000000e+00" res="-3.9054200169630349e-04" rms="8.3651548624038696e-01" />
              </Node>
            </Node>
            <Node Cut="7.0000000000000000e+00" IVar="0" NCoef="0" cType="1" depth="3" nType="0" pos="r" purity="0.0000000000000000e+00" res="1.6183262050617486e-04" rms="8.8814717531204224e-01">
              <Node Cut="5.0000000000000000e+00" IVar="6" NCoef="0" cType="1" depth="4" nType="0" pos="l" purity="0.0000000000000000e+00" res="-1.0932047734968364e-04" rms="9.0482890605926514e-01">
                <Node Cut="0.0000000000000000e+00" IVar="-1" NCoef="0" cType="1" depth="5" nType="-99" pos="l" purity="0.0000000000000000e+00" res="5.1784845709335059e-05" rms="8.9470106363296509e-01" />
                <Node Cut="0.0000000000000000e+00" IVar="-1" NCoef="0" cType="1" depth="5" nType="-99" pos="r" purity="0.0000000000000000e+00" res="-2.1126994397491217e-04" rms="9.3644434213638306e-01" />
              </Node>
              <Node Cut="6.0000000000000000e+00" IVar="5" NCoef="0" cType="1" depth="4" nType="0" pos="r" purity="0.0000000000000000e+00" res="3.4780605346895754e-04" rms="6.6165739297866821e-01">
                <Node Cut="0.0000000000000000e+00" IVar="-1" NCoef="0" cType="1" depth="5" nType="-99" pos="l" purity="0.0000000000000000e+00" res="5.3501105867326260e-05" rms="8.5237151384353638e-01" />
                <Node Cut="0.0000000000000000e+00" IVar="-1" NCoef="0" cType="1" depth="5" nType="-99" pos="r" purity="0.0000000000000000e+00" res="2.0705310162156820e-03" rms="1.0545754432678223e+00" />
              </Node>
            </Node>
          </Node>
          <Node Cut="1.6000000000000000e+01" IVar="0" NCoef="0" cType="1" depth="2" nType="0" pos="r" purity="0.0000000000000000e+00" res="-1.0810044594109058e-02" rms="9.3175852298736572e-01">
            <Node Cut="5.0000000000000000e+00" IVar="5" NCoef="0" cType="1" depth="3" nType="0" pos="l" purity="0.0000000000000000e+00" res="-1.6468534246087074e-02" rms="8.5514378547668457e-01">
              <Node Cut="1.0000000000000000e+00" IVar="2" NCoef="0" cType="1" depth="4" nType="0" pos="l" purity="0.0000000000000000e+00" res="-7.5663272291421890e-03" rms="5.5195182561874390e-01">
                <Node Cut="0.0000000000000000e+00" IVar="-1" NCoef="0" cType="1" depth="5" nType="-99" pos="l" purity="0.0000000000000000e+00" res="2.9843684751540422e-03" rms="1.0614628791809082e+00" />
                <Node Cut="0.0000000000000000e+00" IVar="-1" NCoef="0" cType="1" depth="5" nType="-99" pos="r" purity="0.0000000000000000e+00" res="-3.7631981540471315e-03" rms="9.1854232549667358e-01" />
              </Node>
              <Node Cut="8.0000000000000000e+00" IVar="0" NCoef="0" cType="1" depth="4" nType="0" pos="r" purity="0.0000000000000000e+00" res="-6.1132349073886871e-02" rms="7.5049251317977905e-01">
                <Node Cut="0.0000000000000000e+00" IVar="-1" NCoef="0" cType="1" depth="5" nType="-99" pos="l" purity="0.0000000000000000e+00" res="-3.4963400103151798e-03" rms="8.0485880374908447e-01" />
                <Node Cut="0.0000000000000000e+00" IVar="-1" NCoef="0" cType="1" depth="5" nType="-99" pos="r" purity="0.0000000000000000e+00" res="-1.5387780964374542e-02" rms="5.0251936912536621e-01" />
              </Node>
            </Node>
            <Node Cut="3.0000000000000000e+00" IVar="1" NCoef="0" cType="1" depth="3" nType="0" pos="r" purity="0.0000000000000000e+00" res="0.0000000000000000e+00" rms="0.0000000000000000e+00">
              <Node Cut="6.0000000000000000e+00" IVar="6" NCoef="0" cType="1" depth="4" nType="0" pos="l" purity="0.0000000000000000e+00" res="5.0080604553222656e+00" rms="-nan">
                <Node Cut="0.0000000000000000e+00" IVar="-1" NCoef="0" cType="1" depth="5" nType="-99" pos="l" purity="0.0000000000000000e+00" res="-1.8597841262817383e-02" rms="8.2632571458816528e-01" />
                <Node Cut="0.0000000000000000e+00" IVar="-1" NCoef="0" cType="1" depth="5" nType="-99" pos="r" purity="0.0000000000000000e+00" res="5.6596130132675171e-02" rms="9.4270205497741699e-01" />
              </Node>
              <Node Cut="4.0000000000000000e+00" IVar="1" NCoef="0" cType="1" depth="4" nType="0" pos="r" purity="0.0000000000000000e+00" res="0.0000000000000000e+00" rms="0.0000000000000000e+00">
                <Node Cut="0.0000000000000000e+00" IVar="-1" NCoef="0" cType="1" depth="5" nType="-99" pos="l" purity="0.0000000000000000e+00" res="1.4551004767417908e-01" rms="8.3037060499191284e-01" />
                <Node Cut="0.0000000000000000e+00" IVar="-1" NCoef="0" cType="1" depth="5" nType="-99" pos="r" purity="0.0000000000000000e+00" res="1.2506578117609024e-02" rms="8.6889195442199707e-01" />
              </Node>
            </Node>
          </Node>
        </Node>
        <Node Cut="5.4000000000000000e+01" IVar="1" NCoef="0" cType="1" depth="1" nType="0" pos="r" purity="0.0000000000000000e+00" res="0.0000000000000000e+00" rms="0.0000000000000000e+00">
          <Node Cut="2.0000000000000000e+00" IVar="0" NCoef="0" cType="1" depth="2" nType="0" pos="l" purity="0.0000000000000000e+00" res="-7.1040964685380459e-03" rms="5.0975137948989868e-01">
            <Node Cut="5.3000000000000000e+01" IVar="1" NCoef="0" cType="1" depth="3" nType="0" pos="l" purity="0.0000000000000000e+00" res="0.0000000000000000e+00" rms="0.0000000000000000e+00">
              <Node Cut="5.0000000000000000e+00" IVar="6" NCoef="0" cType="1" depth="4" nType="0" pos="l" purity="0.0000000000000000e+00" res="-2.7810217812657356e-02" rms="7.7491104602813721e-01">
                <Node Cut="0.0000000000000000e+00" IVar="-1" NCoef="0" cType="1" depth="5" nType="-99" pos="l" purity="0.0000000000000000e+00" res="-8.0105662345886230e-03" rms="9.8775345087051392e-01" />
                <Node Cut="0.0000000000000000e+00" IVar="-1" NCoef="0" cType="1" depth="5" nType="-99" pos="r" purity="0.0000000000000000e+00" res="7.7185402624309063e-03" rms="7.4547630548477173e-01" />
              </Node>
              <Node Cut="7.0000000000000000e+00" IVar="6" NCoef="0" cType="1" depth="4" nType="0" pos="r" purity="0.0000000000000000e+00" res="0.0000000000000000e+00" rms="0.0000000000000000e+00">
                <Node Cut="0.0000000000000000e+00" IVar="-1" NCoef="0" cType="1" depth="5" nType="-99" pos="l" purity="0.0000000000000000e+00" res="-2.4262001737952232e-02" rms="8.6250364780426025e-01" />
                <Node Cut="0.0000000000000000e+00" IVar="-1" NCoef="0" cType="1" depth="5" nType="-99" pos="r" purity="0.0000000000000000e+00" res="7.0588350296020508e-01" rms="0.0000000000000000e+00" />
              </Node>
            </Node>
            <Node Cut="2.1000000000000000e+01" IVar="0" NCoef="0" cType="1" depth="3" nType="0" pos="r" purity="0.0000000000000000e+00" res="-5.4825502447783947e-03" rms="4.8847854137420654e-01">
              <Node Cut="1.0000000000000000e+00" IVar="8" NCoef="0" cType="1" depth="4" nType="0" pos="l" purity="0.0000000000000000e+00" res="-1.0497057810425758e-03" rms="2.8997963666915894e-01">
                <Node Cut="0.0000000000000000e+00" IVar="-1" NCoef="0" cType="1" depth="5" nType="-99" pos="l" purity="0.0000000000000000e+00" res="-6.6994072403758764e-04" rms="4.7946199774742126e-01" />
                <Node Cut="0.0000000000000000e+00" IVar="-1" NCoef="0" cType="1" depth="5" nType="-99" pos="r" purity="0.0000000000000000e+00" res="3.7108771502971649e-03" rms="8.0322545766830444e-01" />
              </Node>
              <Node Cut="4.0000000000000000e+00" IVar="4" NCoef="0" cType="1" depth="4" nType="0" pos="r" purity="0.0000000000000000e+00" res="0.0000000000000000e+00" rms="0.0000000000000000e+00">
                <Node Cut="0.0000000000000000e+00" IVar="-1" NCoef="0" cType="1" depth="5" nType="-99" pos="l" purity="0.0000000000000000e+00" res="1.4595459401607513e-01" rms="5.7613778114318848e-01" />
                <Node Cut="0.0000000000000000e+00" IVar="-1" NCoef="0" cType="1" depth="5" nType="-99" pos="r" purity="0.0000000000000000e+00" res="7.3953028768301010e-03" rms="4.3508246541023254e-01" />
              </Node>
            </Node>
          </Node>
          <Node Cut="6.0000000000000000e+00" IVar="6" NCoef="0" cType="1" depth="2" nType="0" pos="r" purity="0.0000000000000000e+00" res="-4.2772342567332089e-05" rms="3.6428982019424438e-01">
            <Node Cut="1.0000000000000000e+00" IVar="3" NCoef="0" cType="1" depth="3" nType="0" pos="l" purity="0.0000000000000000e+00" res="2.1381531041697599e-05" rms="2.3875562846660614e-01">
              <Node Cut="7.0000000000000000e+00" IVar="5" NCoef="0" cType="1" depth="4" nType="0" pos="l" purity="0.0000000000000000e+00" res="1.2133579002693295e-03" rms="3.9430084824562073e-01">
                <Node Cut="0.0000000000000000e+00" IVar="-1" NCoef="0" cType="1" depth="5" nType="-99" pos="l" purity="0.0000000000000000e+00" res="1.1127496691187844e-05" rms="4.0282076597213745e-01" />
                <Node Cut="0.0000000000000000e+00" IVar="-1" NCoef="0" cType="1" depth="5" nType="-99" pos="r" purity="0.0000000000000000e+00" res="1.4237888390198350e-03" rms="7.9182678461074829e-01" />
              </Node>
              <Node Cut="4.0000000000000000e+00" IVar="6" NCoef="0" cType="1" depth="4" nType="0" pos="r" purity="0.0000000000000000e+00" res="-1.6096954932436347e-03" rms="3.1377291679382324e-01">
                <Node Cut="0.0000000000000000e+00" IVar="-1" NCoef="0" cType="1" depth="5" nType="-99" pos="l" purity="0.0000000000000000e+00" res="4.2114153620786965e-04" rms="3.2793438434600830e-01" />
                <Node Cut="0.0000000000000000e+00" IVar="-1" NCoef="0" cType="1" depth="5" nType="-99" pos="r" purity="0.0000000000000000e+00" res="-3.8846689858473837e-04" rms="3.6455395817756653e-01" />
              </Node>
            </Node>
            <Node Cut="1.0000000000000000e+00" IVar="3" NCoef="0" cType="1" depth="3" nType="0" pos="r" purity="0.0000000000000000e+00" res="3.1770291388966143e-04" rms="2.2062478959560394e-01">
              <Node Cut="5.0000000000000000e+00" IVar="5" NCoef="0" cType="1" depth="4" nType="0" pos="l" purity="0.0000000000000000e+00" res="-7.2623603045940399e-04" rms="3.7909033894538879e-01">
                <Node Cut="0.0000000000000000e+00" IVar="-1" NCoef="0" cType="1" depth="5" nType="-99" pos="l" purity="0.0000000000000000e+00" res="4.1429480188526213e-04" rms="7.3122239112854004e-01" />
                <Node Cut="0.0000000000000000e+00" IVar="-1" NCoef="0" cType="1" depth="5" nType="-99" pos="r" purity="0.0000000000000000e+00" res="-1.1952004861086607e-03" rms="3.5646346211433411e-01" />
              </Node>
              <Node Cut="7.0000000000000000e+00" IVar="5" NCoef="0" cType="1" depth="4" nType="0" pos="r" purity="0.0000000000000000e+00" res="7.3535679839551449e-03" rms="2.9699891805648804e-01">
                <Node Cut="0.0000000000000000e+00" IVar="-1" NCoef="0" cType="1" depth="5" nType="-99" pos="l" purity="0.0000000000000000e+00" res="1.5970873646438122e-03" rms="4.1457590460777283e-01" />
                <Node Cut="0.0000000000000000e+00" IVar="-1" NCoef="0" cType="1" depth="5" nType="-99" pos="r" purity="0.0000000000000000e+00" res="-1.3896070886403322e-03" rms="2.9539489746093750e-01" />
              </Node>
            </Node>
          </Node>
        </Node>
      </Node>
    </BinaryTree>
    