<?xml version="1.0"?>
<BinaryTree boostWeight="1.0000000000000000e+00" itree="134" type="DecisionTree">
      <Node Cut="1.9000000000000000e+01" IVar="0" NCoef="0" cType="1" depth="0" nType="0" pos="s" purity="0.0000000000000000e+00" res="3.0160630937192678e-11" rms="3.2924565672874451e-01">
        <Node Cut="0.0000000000000000e+00" IVar="6" NCoef="0" cType="1" depth="1" nType="0" pos="l" purity="0.0000000000000000e+00" res="0.0000000000000000e+00" rms="0.0000000000000000e+00">
          <Node Cut="0.0000000000000000e+00" IVar="5" NCoef="0" cType="1" depth="2" nType="0" pos="l" purity="0.0000000000000000e+00" res="0.0000000000000000e+00" rms="0.0000000000000000e+00">
            <Node Cut="3.9200000000000000e+02" IVar="2" NCoef="0" cType="1" depth="3" nType="0" pos="l" purity="0.0000000000000000e+00" res="0.0000000000000000e+00" rms="0.0000000000000000e+00">
              <Node Cut="2.0000000000000000e+00" IVar="7" NCoef="0" cType="1" depth="4" nType="0" pos="l" purity="0.0000000000000000e+00" res="3.4892376512289047e-02" rms="4.1783940792083740e-01">
                <Node Cut="0.0000000000000000e+00" IVar="-1" NCoef="0" cType="1" depth="5" nType="-99" pos="l" purity="0.0000000000000000e+00" res="-1.4129485934972763e-03" rms="2.8888541460037231e-01" />
                <Node Cut="0.0000000000000000e+00" IVar="-1" NCoef="0" cType="1" depth="5" nType="-99" pos="r" purity="0.0000000000000000e+00" res="4.8798881471157074e-03" rms="4.6040782332420349e-01" />
              </Node>
              <Node Cut="8.0000000000000000e+00" IVar="0" NCoef="0" cType="1" depth="4" nType="0" pos="r" purity="0.0000000000000000e+00" res="5.7802104856818914e-04" rms="2.4963760375976562e-01">
                <Node Cut="0.0000000000000000e+00" IVar="-1" NCoef="0" cType="1" depth="5" nType="-99" pos="l" purity="0.0000000000000000e+00" res="2.2233015624806285e-04" rms="2.4974961578845978e-01" />
                <Node Cut="0.0000000000000000e+00" IVar="-1" NCoef="0" cType="1" depth="5" nType="-99" pos="r" purity="0.0000000000000000e+00" res="-1.0660627856850624e-02" rms="2.1681827306747437e-01" />
              </Node>
            </Node>
            <Node Cut="2.0000000000000000e+00" IVar="7" NCoef="0" cType="1" depth="3" nType="0" pos="r" purity="0.0000000000000000e+00" res="-4.2940899729728699e-03" rms="2.5341215729713440e-01">
              <Node Cut="1.0000000000000000e+00" IVar="5" NCoef="0" cType="1" depth="4" nType="0" pos="l" purity="0.0000000000000000e+00" res="3.0025914311408997e-03" rms="1.4137186110019684e-01">
                <Node Cut="0.0000000000000000e+00" IVar="-1" NCoef="0" cType="1" depth="5" nType="-99" pos="l" purity="0.0000000000000000e+00" res="-1.2073823250830173e-02" rms="3.1671634316444397e-01" />
                <Node Cut="0.0000000000000000e+00" IVar="-1" NCoef="0" cType="1" depth="5" nType="-99" pos="r" purity="0.0000000000000000e+00" res="9.0348016237840056e-04" rms="1.6127543151378632e-01" />
              </Node>
              <Node Cut="6.0000000000000000e+00" IVar="7" NCoef="0" cType="1" depth="4" nType="0" pos="r" purity="0.0000000000000000e+00" res="-1.0748577304184437e-02" rms="2.7945926785469055e-01">
                <Node Cut="0.0000000000000000e+00" IVar="-1" NCoef="0" cType="1" depth="5" nType="-99" pos="l" purity="0.0000000000000000e+00" res="-1.5163493808358908e-03" rms="3.2991996407508850e-01" />
                <Node Cut="0.0000000000000000e+00" IVar="-1" NCoef="0" cType="1" depth="5" nType="-99" pos="r" purity="0.0000000000000000e+00" res="1.0431264527142048e-03" rms="2.1250317990779877e-01" />
              </Node>
            </Node>
          </Node>
          <Node Cut="2.0000000000000000e+00" IVar="5" NCoef="0" cType="1" depth="2" nType="0" pos="r" purity="0.0000000000000000e+00" res="0.0000000000000000e+00" rms="0.0000000000000000e+00">
            <Node Cut="0.0000000000000000e+00" IVar="5" NCoef="0" cType="1" depth="3" nType="0" pos="l" purity="0.0000000000000000e+00" res="0.0000000000000000e+00" rms="0.0000000000000000e+00">
              <Node Cut="1.6900000000000000e+02" IVar="2" NCoef="0" cType="1" depth="4" nType="0" pos="l" purity="0.0000000000000000e+00" res="0.0000000000000000e+00" rms="0.0000000000000000e+00">
                <Node Cut="0.0000000000000000e+00" IVar="-1" NCoef="0" cType="1" depth="5" nType="-99" pos="l" purity="0.0000000000000000e+00" res="-6.8276200909167528e-04" rms="3.0395096540451050e-01" />
                <Node Cut="0.0000000000000000e+00" IVar="-1" NCoef="0" cType="1" depth="5" nType="-99" pos="r" purity="0.0000000000000000e+00" res="1.2830579362343997e-04" rms="2.2916425764560699e-01" />
              </Node>
              <Node Cut="2.0000000000000000e+00" IVar="7" NCoef="0" cType="1" depth="4" nType="0" pos="r" purity="0.0000000000000000e+00" res="9.9244108423590660e-03" rms="5.2588534355163574e-01">
                <Node Cut="0.0000000000000000e+00" IVar="-1" NCoef="0" cType="1" depth="5" nType="-99" pos="l" purity="0.0000000000000000e+00" res="-3.1724472064524889e-03" rms="2.9553306102752686e-01" />
                <Node Cut="0.0000000000000000e+00" IVar="-1" NCoef="0" cType="1" depth="5" nType="-99" pos="r" purity="0.0000000000000000e+00" res="1.8914864631369710e-03" rms="5.7303011417388916e-01" />
              </Node>
            </Node>
            <Node Cut="3.6200000000000000e+02" IVar="2" NCoef="0" cType="1" depth="3" nType="0" pos="r" purity="0.0000000000000000e+00" res="0.0000000000000000e+00" rms="-nan">
              <Node Cut="4.0000000000000000e+00" IVar="5" NCoef="0" cType="1" depth="4" nType="0" pos="l" purity="0.0000000000000000e+00" res="-2.9339522123336792e-02" rms="2.6527136564254761e-01">
                <Node Cut="0.0000000000000000e+00" IVar="-1" NCoef="0" cType="1" depth="5" nType="-99" pos="l" purity="0.0000000000000000e+00" res="-5.5921389721333981e-03" rms="3.3830529451370239e-01" />
                <Node Cut="0.0000000000000000e+00" IVar="-1" NCoef="0" cType="1" depth="5" nType="-99" pos="r" purity="0.0000000000000000e+00" res="8.4664784371852875e-03" rms="5.1143127679824829e-01" />
              </Node>
              <Node Cut="8.0000000000000000e+00" IVar="0" NCoef="0" cType="1" depth="4" nType="0" pos="r" purity="0.0000000000000000e+00" res="9.5715885981917381e-03" rms="2.0807047188282013e-01">
                <Node Cut="0.0000000000000000e+00" IVar="-1" NCoef="0" cType="1" depth="5" nType="-99" pos="l" purity="0.0000000000000000e+00" res="1.6129401046782732e-03" rms="2.1162882447242737e-01" />
                <Node Cut="0.0000000000000000e+00" IVar="-1" NCoef="0" cType="1" depth="5" nType="-99" pos="r" purity="0.0000000000000000e+00" res="-4.6690478920936584e-03" rms="1.6415278613567352e-01" />
              </Node>
            </Node>
          </Node>
        </Node>
        <Node Cut="0.0000000000000000e+00" IVar="6" NCoef="0" cType="1" depth="1" nType="0" pos="r" purity="0.0000000000000000e+00" res="0.0000000000000000e+00" rms="0.0000000000000000e+00">
          <Node Cut="1.4800000000000000e+02" IVar="2" NCoef="0" cType="1" depth="2" nType="0" pos="l" purity="0.0000000000000000e+00" res="0.0000000000000000e+00" rms="0.0000000000000000e+00">
            <Node Cut="3.0000000000000000e+00" IVar="5" NCoef="0" cType="1" depth="3" nType="0" pos="l" purity="0.0000000000000000e+00" res="0.0000000000000000e+00" rms="0.0000000000000000e+00">
              <Node Cut="4.0000000000000000e+00" IVar="7" NCoef="0" cType="1" depth="4" nType="0" pos="l" purity="0.0000000000000000e+00" res="3.5201787948608398e-02" rms="2.7346268296241760e-01">
                <Node Cut="0.0000000000000000e+00" IVar="-1" NCoef="0" cType="1" depth="5" nType="-99" pos="l" purity="0.0000000000000000e+00" res="2.9589871410280466e-03" rms="2.3615802824497223e-01" />
                <Node Cut="0.0000000000000000e+00" IVar="-1" NCoef="0" cType="1" depth="5" nType="-99" pos="r" purity="0.0000000000000000e+00" res="1.0364897549152374e-02" rms="5.6502389907836914e-01" />
              </Node>
              <Node Cut="-1.0000000000000000e+00" IVar="6" NCoef="0" cType="1" depth="4" nType="0" pos="r" purity="0.0000000000000000e+00" res="0.0000000000000000e+00" rms="0.0000000000000000e+00">
                <Node Cut="0.0000000000000000e+00" IVar="-1" NCoef="0" cType="1" depth="5" nType="-99" pos="l" purity="0.0000000000000000e+00" res="2.2044268553145230e-04" rms="1.2405920028686523e-01" />
                <Node Cut="0.0000000000000000e+00" IVar="-1" NCoef="0" cType="1" depth="5" nType="-99" pos="r" purity="0.0000000000000000e+00" res="4.2072287760674953e-03" rms="1.2824359536170959e-01" />
              </Node>
            </Node>
            <Node Cut="5.0000000000000000e+00" IVar="7" NCoef="0" cType="1" depth="3" nType="0" pos="r" purity="0.0000000000000000e+00" res="0.0000000000000000e+00" rms="0.0000000000000000e+00">
              <Node Cut="3.9200000000000000e+02" IVar="2" NCoef="0" cType="1" depth="4" nType="0" pos="l" purity="0.0000000000000000e+00" res="2.7771270833909512e-04" rms="1.6662400215864182e-02">
                <Node Cut="0.0000000000000000e+00" IVar="-1" NCoef="0" cType="1" depth="5" nType="-99" pos="l" purity="0.0000000000000000e+00" res="-1.8511585949454457e-05" rms="1.4521613717079163e-01" />
                <Node Cut="0.0000000000000000e+00" IVar="-1" NCoef="0" cType="1" depth="5" nType="-99" pos="r" purity="0.0000000000000000e+00" res="1.2946870177984238e-02" rms="1.2029022723436356e-01" />
              </Node>
              <Node Cut="-1.0000000000000000e+00" IVar="6" NCoef="0" cType="1" depth="4" nType="0" pos="r" purity="0.0000000000000000e+00" res="0.0000000000000000e+00" rms="0.0000000000000000e+00">
                <Node Cut="0.0000000000000000e+00" IVar="-1" NCoef="0" cType="1" depth="5" nType="-99" pos="l" purity="0.0000000000000000e+00" res="-5.7560219429433346e-03" rms="1.5236783027648926e-01" />
                <Node Cut="0.0000000000000000e+00" IVar="-1" NCoef="0" cType="1" depth="5" nType="-99" pos="r" purity="0.0000000000000000e+00" res="-4.1197542101144791e-02" rms="7.9883992671966553e-02" />
              </Node>
            </Node>
          </Node>
          <Node Cut="1.0000000000000000e+00" IVar="5" NCoef="0" cType="1" depth="2" nType="0" pos="r" purity="0.0000000000000000e+00" res="0.0000000000000000e+00" rms="0.0000000000000000e+00">
            <Node Cut="2.1000000000000000e+01" IVar="2" NCoef="0" cType="1" depth="3" nType="0" pos="l" purity="0.0000000000000000e+00" res="0.0000000000000000e+00" rms="0.0000000000000000e+00">
              <Node Cut="0.0000000000000000e+00" IVar="5" NCoef="0" cType="1" depth="4" nType="0" pos="l" purity="0.0000000000000000e+00" res="0.0000000000000000e+00" rms="0.0000000000000000e+00">
                <Node Cut="0.0000000000000000e+00" IVar="-1" NCoef="0" cType="1" depth="5" nType="-99" pos="l" purity="0.0000000000000000e+00" res="2.4600629694759846e-03" rms="2.5915062427520752e-01" />
                <Node Cut="0.0000000000000000e+00" IVar="-1" NCoef="0" cType="1" depth="5" nType="-99" pos="r" purity="0.0000000000000000e+00" res="4.3540406972169876e-02" rms="9.8987722396850586e-01" />
              </Node>
              <Node Cut="1.0000000000000000e+00" IVar="6" NCoef="0" cType="1" depth="4" nType="0" pos="r" purity="0.0000000000000000e+00" res="3.1613504979759455e-03" rms="1.9702754914760590e-01">
                <Node Cut="0.0000000000000000e+00" IVar="-1" NCoef="0" cType="1" depth="5" nType="-99" pos="l" purity="0.0000000000000000e+00" res="-3.5591570194810629e-03" rms="3.3289560675621033e-01" />
                <Node Cut="0.0000000000000000e+00" IVar="-1" NCoef="0" cType="1" depth="5" nType="-99" pos="r" purity="0.0000000000000000e+00" res="9.1801030794158578e-04" rms="1.7333869636058807e-01" />
              </Node>
            </Node>
            <Node Cut="2.0000000000000000e+00" IVar="5" NCoef="0" cType="1" depth="3" nType="0" pos="r" purity="0.0000000000000000e+00" res="-5.1814205944538116e-02" rms="2.7818706631660461e-01">
              <Node Cut="2.1000000000000000e+01" IVar="0" NCoef="0" cType="1" depth="4" nType="0" pos="l" purity="0.0000000000000000e+00" res="-1.0902415215969086e-01" rms="3.9790299534797668e-01">
                <Node Cut="0.0000000000000000e+00" IVar="-1" NCoef="0" cType="1" depth="5" nType="-99" pos="l" purity="0.0000000000000000e+00" res="-1.7438212409615517e-02" rms="3.8983353972434998e-01" />
                <Node Cut="0.0000000000000000e+00" IVar="-1" NCoef="0" cType="1" depth="5" nType="-99" pos="r" purity="0.0000000000000000e+00" res="-5.0606555305421352e-03" rms="3.9595165848731995e-01" />
              </Node>
              <Node Cut="6.0000000000000000e+01" IVar="2" NCoef="0" cType="1" depth="4" nType="0" pos="r" purity="0.0000000000000000e+00" res="8.8988855481147766e-02" rms="-nan">
                <Node Cut="0.0000000000000000e+00" IVar="-1" NCoef="0" cType="1" depth="5" nType="-99" pos="l" purity="0.0000000000000000e+00" res="-1.3884094543755054e-02" rms="3.3367308974266052e-01" />
                <Node Cut="0.0000000000000000e+00" IVar="-1" NCoef="0" cType="1" depth="5" nType="-99" pos="r" purity="0.0000000000000000e+00" res="2.1872390061616898e-03" rms="1.8940852582454681e-01" />
              </Node>
            </Node>
          </Node>
        </Node>
      </Node>
    </BinaryTree>
    